woopyMysql/__init__.py
woopyMysql/woopymysql.py
woopyMysql-0.1.dist-info/LICENSE.md
woopyMysql-0.1.dist-info/METADATA
woopyMysql-0.1.dist-info/WHEEL
woopyMysql-0.1.dist-info/top_level.txt
woopyMysql-0.1.dist-info/RECORD
