Metadata-Version: 2.1
Name: woopyMysql
Version: 0.1
Summary: Simple class to manage multiple Mysql Db with mysql-connector-python
Home-page: https://www.wppy.net
Author: Woopy
Author-email: woopygit@icloud.com
Classifier: Programming Language :: Python :: 3
Classifier: License :: OSI Approved :: MIT License
Classifier: Operating System :: OS Independent
Requires-Python: >=3.6, <3.13
License-File: LICENSE.md
Requires-Dist: mysql-connector-python
Requires-Dist: python-dotenv
